vsatcloud/__init__.py
vsatcloud/common.py
vsatcloud/logging.py
vsatcloud/scene.py
vsatcloud-0.1.0.dist-info/METADATA
vsatcloud-0.1.0.dist-info/WHEEL
vsatcloud-0.1.0.dist-info/top_level.txt
vsatcloud-0.1.0.dist-info/zip-safe
vsatcloud-0.1.0.dist-info/RECORD
