Metadata-Version: 2.1
Name: vsatcloud
Version: 0.1.0
Summary: vsat-cloud python sdk
Home-page: https://vsat.cloud
Author: vsattech.com
Author-email: it@vsattech.com
License: UNKNOWN
Platform: UNKNOWN
Classifier: Programming Language :: Python :: 3
Classifier: Operating System :: OS Independent
Requires-Dist: requests (>=2.19.1)
